tests/__init__.py
tests/test_valido_decorators.py
valido/__init__.py
valido/valido_decorators.py
valido-0.1.0.dist-info/LICENSE
valido-0.1.0.dist-info/METADATA
valido-0.1.0.dist-info/WHEEL
valido-0.1.0.dist-info/top_level.txt
valido-0.1.0.dist-info/RECORD
