Metadata-Version: 2.1
Name: valido
Version: 0.1.0
Summary: PySpark dataframes based workflow validator
Home-page: UNKNOWN
Author: Souvik Pratiher
Author-email: spratiher9@gmail.com
License: UNKNOWN
Platform: UNKNOWN
Classifier: Development Status :: 5 - Production/Stable
Classifier: Programming Language :: Python :: 3.8
Classifier: Programming Language :: Python :: 3.9
Classifier: Programming Language :: Python :: 3.10
Classifier: License :: OSI Approved :: BSD License
Classifier: Operating System :: OS Independent
Requires-Python: >=3.8
License-File: LICENSE
Requires-Dist: atomicwrites
Requires-Dist: attrs
Requires-Dist: colorama
Requires-Dist: iniconfig
Requires-Dist: numpy
Requires-Dist: packaging
Requires-Dist: pandas
Requires-Dist: pluggy
Requires-Dist: py
Requires-Dist: py4j
Requires-Dist: pyparsing
Requires-Dist: pyspark
Requires-Dist: pytest
Requires-Dist: pytest-mock
Requires-Dist: python-dateutil
Requires-Dist: pytz
Requires-Dist: six
Requires-Dist: toml
